tvalmetrics/__init__.py
tvalmetrics/llm_calls.py
tvalmetrics/openai_api_util.py
tvalmetrics/rag_scores_calculator.py
tvalmetrics/scorers/__init__.py
tvalmetrics/scorers/answer_consistency_binary_scorer.py
tvalmetrics/scorers/answer_consistency_scorer.py
tvalmetrics/scorers/answer_similarity_scorer.py
tvalmetrics/scorers/augmentation_accuracy_scorer.py
tvalmetrics/scorers/augmentation_precision_scorer.py
tvalmetrics/scorers/context_scorer.py
tvalmetrics/scorers/retrieval_k_recall_scorer.py
tvalmetrics/scorers/retrieval_precision_scorer.py
tvalmetrics/scorers/scorers_util.py
tvalmetrics-1.0.2.dist-info/LICENSE
tvalmetrics-1.0.2.dist-info/METADATA
tvalmetrics-1.0.2.dist-info/WHEEL
tvalmetrics-1.0.2.dist-info/RECORD
