Metadata-Version: 2.1
Name: tvalmetrics
Version: 1.0.2
Summary: RAG evaluation metrics.
Author: Joe Ferrara
Author-email: joeferrara@tonic.ai
Requires-Python: >=3.8.1,<4.0.0
Classifier: Programming Language :: Python :: 3
Classifier: Programming Language :: Python :: 3.9
Classifier: Programming Language :: Python :: 3.10
Classifier: Programming Language :: Python :: 3.11
Classifier: Programming Language :: Python :: 3.12
Requires-Dist: openai (>=1.0.0)
Requires-Dist: pandas (>=1.2.3)
